tidy_viewer_py-0.3.0.dist-info/METADATA
tidy_viewer_py-0.3.0.dist-info/WHEEL
tidy_viewer_py/__init__.py
tidy_viewer_py/_core.cpython-313-darwin.so
tidy_viewer_py/dtype_mapping.py
tidy_viewer_py-0.3.0.dist-info/RECORD
