Metadata-Version: 2.4
Name: tidy-viewer-py
Version: 0.3.0
Classifier: Development Status :: 4 - Beta
Classifier: Intended Audience :: Developers
Classifier: License :: OSI Approved :: MIT License
Classifier: License :: OSI Approved :: Apache Software License
Classifier: Programming Language :: Python :: 3
Classifier: Programming Language :: Python :: 3.8
Classifier: Programming Language :: Python :: 3.9
Classifier: Programming Language :: Python :: 3.10
Classifier: Programming Language :: Python :: 3.11
Classifier: Programming Language :: Python :: 3.12
Classifier: Programming Language :: Python :: Implementation :: CPython
Classifier: Programming Language :: Rust
Classifier: Operating System :: OS Independent
Classifier: Topic :: Software Development :: Libraries :: Python Modules
Classifier: Topic :: Text Processing :: General
Requires-Dist: maturin>=1.9.3
Requires-Dist: pandas>=2.0.3
Requires-Dist: polars>=1.8.2
Requires-Dist: pyarrow>=17.0.0
Requires-Dist: pytest>=8.3.5
Requires-Dist: pytest>=7.0 ; extra == 'dev'
Requires-Dist: pytest-benchmark ; extra == 'dev'
Requires-Dist: pandas>=1.0 ; extra == 'dev'
Requires-Dist: pyarrow>=10.0 ; extra == 'dev'
Requires-Dist: ruff ; extra == 'dev'
Requires-Dist: mypy ; extra == 'dev'
Provides-Extra: dev
Summary: A cross-platform data pretty printer that uses column styling to maximize viewer enjoyment. Supports CSV, Parquet, Pandas, and Polars DataFrames with automatic data type detection and display.
Keywords: table,formatting,terminal,pretty-print,csv,parquet
Author-email: Alex Hallam <alexhallam6.28@gmail.com>
License: MIT OR Apache-2.0
Requires-Python: >=3.8
Project-URL: Homepage, https://github.com/yourusername/tidy-viewer-py
Project-URL: Repository, https://github.com/yourusername/tidy-viewer-py
Project-URL: Issues, https://github.com/yourusername/tidy-viewer-py/issues
